<?xml version="1.0" encoding="UTF-8"?>
<basicInfo>
    <newInfo>
        <cdnId>BJ-website-wyy</cdnId>
        <customerInfo>
            <customerId>QEcM7yf2ot4WAN81</customerId>
            <unitName>风度仕服饰</unitName>
            <unitNature>4</unitNature>
            <idType>1</idType>
            <idNumber>62458793412758</idNumber>
            <Add>中关村大街2号楼</Add>
            <serviceInfo>
                <serviceId>YGKxtDpFBNVdgD4f</serviceId>
                <serviceContent>9</serviceContent>
                <domainInfo>
                    <domainId>6SPVcKuXawHfo4EP</domainId>
                    <domain>www.regyu.com</domain>
                    <regId>beijing-8num</regId>
                </domainInfo>
            </serviceInfo>
        </customerInfo>
    </newInfo>
    <timeStamp>2017-03-25 07:07:38</timeStamp>
</basicInfo>
